indastructa-0.1.1.dist-info/licenses/LICENCE
indastructa_pkg/__init__.py
indastructa_pkg/cli.py
indastructa-0.1.1.dist-info/METADATA
indastructa-0.1.1.dist-info/WHEEL
indastructa-0.1.1.dist-info/entry_points.txt
indastructa-0.1.1.dist-info/top_level.txt
indastructa-0.1.1.dist-info/RECORD
