Metadata-Version: 2.4
Name: indastructa
Version: 0.1.1
Summary: A CLI tool to generate ASCII tree representation of a project structure.
Author-email: H-E-L-L-gi <oleg.cegak@gmail.com>
License: MIT License
Project-URL: Source, https://github.com/H-E-L-L-g-i/Indastructa
Classifier: Programming Language :: Python :: 3
Classifier: Programming Language :: Python :: 3.10
Classifier: Programming Language :: Python :: 3.11
Classifier: Programming Language :: Python :: 3.12
Classifier: Operating System :: OS Independent
Classifier: Topic :: Utilities
Requires-Python: >=3.10
License-File: LICENCE
Dynamic: license-file
